rootstacks/LICENSE
rootstacks/README.MD
rootstacks/__init__.py
rootstacks/requirements.txt
rootstacks/thirdparty.json
rootstacks-0.12.dist-info/LICENSE.rst
rootstacks-0.12.dist-info/METADATA
rootstacks-0.12.dist-info/WHEEL
rootstacks-0.12.dist-info/top_level.txt
rootstacks-0.12.dist-info/RECORD
